bl_seth/__init__.py
bl_seth/py.typed
bl_seth-0.2.0.dist-info/LICENSE
bl_seth-0.2.0.dist-info/WHEEL
bl_seth-0.2.0.dist-info/METADATA
bl_seth-0.2.0.dist-info/RECORD
