Metadata-Version: 2.1
Name: bl-seth
Version: 0.2.0
Summary: Setting management library
Home-page: https://git.easter-eggs.org/bioneland/bl-seth
License: GPL-3.0-or-later
Author: Tanguy Le Carrour
Author-email: tanguy@bioneland.org
Requires-Python: >=3.9,<4.0
Classifier: License :: OSI Approved :: GNU General Public License v3 or later (GPLv3+)
Classifier: Programming Language :: Python :: 3
Classifier: Programming Language :: Python :: 3.10
Classifier: Programming Language :: Python :: 3.9
Project-URL: Repository, https://git.easter-eggs.org/bioneland/bl-seth
